prefect_docker/__init__.py
prefect_docker/_version.py
prefect_docker/containers.py
prefect_docker/credentials.py
prefect_docker/host.py
prefect_docker/images.py
prefect_docker/types.py
prefect_docker/worker.py
prefect_docker/deployments/__init__.py
prefect_docker/deployments/steps.py
prefect_docker/experimental/__init__.py
prefect_docker/experimental/decorators.py
prefect_docker-0.7.0.dist-info/licenses/LICENSE
prefect_docker-0.7.0.dist-info/METADATA
prefect_docker-0.7.0.dist-info/WHEEL
prefect_docker-0.7.0.dist-info/entry_points.txt
prefect_docker-0.7.0.dist-info/top_level.txt
prefect_docker-0.7.0.dist-info/RECORD
